ottopilot/__init__.py
ottopilot/cli.py
ottopilot/commands.py
ottopilot/log_utils.py
ottopilot-0.0.2.dist-info/METADATA
ottopilot-0.0.2.dist-info/WHEEL
ottopilot-0.0.2.dist-info/entry_points.txt
ottopilot-0.0.2.dist-info/RECORD
