Metadata-Version: 2.4
Name: OttoPilot
Version: 0.0.2
Summary: OttoPilot
Author-email: Ascend <engineering@ascend.io>
Requires-Python: >=3.13
Requires-Dist: rich>=13.0.0
Requires-Dist: typer>=0.9.0
Provides-Extra: dev
Requires-Dist: ruff>=0.1.0; extra == 'dev'
